[
    {
      "id": "e439d051-ddc0-4727-a609-8596b9676178",
      "customerId": "123456789",
      "type": "checking",
      "accountNumber": "0000",
      "agency": "01",
      "status": "open",
      "balance": 0,
      "incomes": [],
      "outcomes": [],
      "creationDate": "2024-08-05T23:59:32.185Z",
      "overdraftLimit": 1000,
      "maintenanceFee": 0.03
    },
    {
      "id": "c6e26164-e4fb-428d-b409-89b914e53828",
      "customerId": "987654321",
      "type": "checking",
      "accountNumber": "0001",
      "agency": "01",
      "status": "open",
      "balance": 0,
      "incomes": [],
      "outcomes": [],
      "creationDate": "2024-08-05T23:59:47.905Z",
      "overdraftLimit": 1000,
      "maintenanceFee": 0.03
    }
  ]